tf_lambda_resnet/__init__.py
tf_lambda_resnet/tf_lambda_resnet.py
tf_lambda_resnet-0.1.4.dist-info/WHEEL
tf_lambda_resnet-0.1.4.dist-info/METADATA
tf_lambda_resnet-0.1.4.dist-info/RECORD
