Metadata-Version: 2.1
Name: tf-lambda-resnet
Version: 0.1.4
Summary: LambdaResNet implementation in TensorFlow 2.2
Home-page: https://github.com/adimyth/tf-lambda-resnet
License: MIT
Keywords: tensorflow,research,deep-learning,lambda-networks,resnet
Author: adimyth
Author-email: mishraaditya6991@gmail.com
Requires-Python: >=3.6.1,<4.0.0
Classifier: Intended Audience :: Developers
Classifier: Intended Audience :: Science/Research
Classifier: License :: OSI Approved :: MIT License
Classifier: Programming Language :: Python :: 3
Classifier: Programming Language :: Python :: 3 :: Only
Classifier: Programming Language :: Python :: 3.6
Classifier: Programming Language :: Python :: 3.7
Classifier: Programming Language :: Python :: 3.8
Classifier: Topic :: Scientific/Engineering
Classifier: Topic :: Scientific/Engineering :: Artificial Intelligence
Classifier: Topic :: Utilities
Requires-Dist: einops (>=0.3.0,<0.4.0)
Requires-Dist: jupyter (>=1.0.0,<2.0.0)
Requires-Dist: pandas (>=1.1.3,<2.0.0)
Requires-Dist: seaborn (>=0.11.0,<0.12.0)
Requires-Dist: sklearn (>=0.0,<0.1)
Requires-Dist: tensorflow (==2.2.0)
Project-URL: Documentation, https://github.com/adimyth/tf-lambda-resnet
Project-URL: Repository, https://github.com/adimyth/tf-lambda-resnet
